arrlp/__init__.py
arrlp/modules/__init__.py
arrlp/modules/compress_LP/__init__.py
arrlp/modules/compress_LP/compress.py
arrlp/modules/compress_LP/functions/__init__.py
arrlp/modules/compress_LP/functions/__template__.py
arrlp/modules/compress_LP/test_compress.py
arrlp/modules/convolve_LP/__init__.py
arrlp/modules/convolve_LP/convolve.py
arrlp/modules/convolve_LP/functions/__init__.py
arrlp/modules/convolve_LP/functions/__template__.py
arrlp/modules/convolve_LP/test_convolve.py
arrlp/modules/coordinates_LP/__init__.py
arrlp/modules/coordinates_LP/coordinates.py
arrlp/modules/coordinates_LP/functions/__init__.py
arrlp/modules/coordinates_LP/functions/__template__.py
arrlp/modules/coordinates_LP/test_coordinates.py
arrlp/modules/correlate_LP/__init__.py
arrlp/modules/correlate_LP/correlate.py
arrlp/modules/correlate_LP/functions/__init__.py
arrlp/modules/correlate_LP/functions/__template__.py
arrlp/modules/correlate_LP/test_correlate.py
arrlp/modules/kernel_LP/__init__.py
arrlp/modules/kernel_LP/functions/__init__.py
arrlp/modules/kernel_LP/functions/__template__.py
arrlp/modules/kernel_LP/kernel.py
arrlp/modules/kernel_LP/test_kernel.py
arrlp/modules/relabel_LP/__init__.py
arrlp/modules/relabel_LP/functions/__init__.py
arrlp/modules/relabel_LP/functions/__template__.py
arrlp/modules/relabel_LP/relabel.py
arrlp/modules/relabel_LP/test_relabel.py
arrlp/modules/xp_LP/__init__.py
arrlp/modules/xp_LP/functions/__init__.py
arrlp/modules/xp_LP/functions/__template__.py
arrlp/modules/xp_LP/test_xp.py
arrlp/modules/xp_LP/xp.py
arrlp/py.typed
arrlp/routines/__init__.py
arrlp-0.1.13.dist-info/WHEEL
arrlp-0.1.13.dist-info/METADATA
arrlp-0.1.13.dist-info/RECORD
