Metadata-Version: 2.3
Name: arrlp
Version: 0.1.13
Summary: A library providing custom functions for arrays.
Requires-Dist: astropy
Requires-Dist: corelp
Requires-Dist: numba
Requires-Dist: numpy
Requires-Dist: scipy
Requires-Python: >=3.12
